{
    "keyBindings":{
        "player1":{
            "87":["moveUp"],
            "83":["moveDown"],
            "65":["moveLeft"],
            "68":["moveRight"],
            "88":["debugger"]
        }
    },
    "assets" : [
        ["pacmanSheet", "pacmanSheet.png"]
    ],
    "startingVertices": {
        "pacman": 22,
        "blueGhost": null,
        "orangeGhost": null,
        "pinkGhost": null,
        "redGhost": null
      },
    "map": [
        {
            "id": 0,
            "x":142,
            "y":28,
            "right": 1,
            "left": 63,
            "down": 67
        },
        {
            "id": 1,
            "x":274,
            "y":28,
            "left": 0,
            "down": 2
        },
        {
            "id": 2,
            "x":274,
            "y":116,
            "right": 3,
            "left": 5,
            "up": 1
        },
        {
            "id": 3,
            "x":340,
            "y":116,
            "right": 55,
            "left": 2,
            "up": 4
        },
        {
            "id": 4,
            "x":340,
            "y":28,
            "right": 52,
            "down": 3
        },
        {
            "id": 5,
            "x":208,
            "y":116,
            "right": 2,
            "left": 67,
            "down": 6
        },
        {
            "id": 6,
            "x":208,
            "y":182,
            "right": 7,
            "up": 5
        },
        {
            "id": 7,
            "x":276,
            "y":182,
            "left": 6,
            "down": 8
        },
        {
            "id": 8,
            "x":274,
            "y":247,
            "right": 10,
            "left": 58,
            "up": 7
        },
        {
            "id": 9,
            "x":340,
            "y":248,
            "right": 12,
            "left": 10,
            "up": 57
        },
        {
            "id": 10,
            "x":307,
            "y":248,
            "right": 9,
            "left": 8,
            "down": 11
        },
        {
            "id": 11,
            "x":307,
            "y":315,
            "up": 10,
            "left":68,
            "right":69
        },
        {
            "id": 12,
            "x":406,
            "y":248,
            "left": 9,
            "down": 13
        },
        {
            "id": 13,
            "x":406,
            "y":315,
            "right": 14,
            "up": 12,
            "down": 47
        },
        {
            "id": 14,
            "x":472,
            "y":315,
            "right": 54,
            "left": 13,
            "up": 48,
            "down": 22
        },
        {
            "id": 15,
            "x":274,
            "y":510,
            "right": 16,
            "left": 43,
            "up": 17
        },
        {
            "id": 16,
            "x":340,
            "y":510,
            "right": 44,
            "left": 15,
            "up": 18
        },
        {
            "id": 17,
            "x":274,
            "y":445,
            "left": 19,
            "down": 15
        },
        {
            "id": 18,
            "x":340,
            "y":445,
            "right": 20,
            "down": 16
        },
        {
            "id": 19,
            "x":208,
            "y":445,
            "right": 17,
            "left": 21,
            "up": 60
        },
        {
            "id": 20,
            "x":406,
            "y":445,
            "right": 22,
            "left": 18,
            "up": 47
        },
        {
            "id": 21,
            "x":142,
            "y":445,
            "right": 19,
            "left": 23,
            "up": 61,
            "down": 41
        },
        {
            "id": 22,
            "x":472,
            "y":445,
            "right": 24,
            "left": 20,
            "up": 14,
            "down": 42
        },
        {
            "id": 23,
            "x":33,
            "y":445,
            "right": 21,
            "down": 25
        },
        {
            "id": 24,
            "x":581,
            "y":445,
            "down": 26,
            "left": 22
        },
        {
            "id": 25,
            "x":33,
            "y":512,
            "right": 27,
            "up": 23
        },
        {
            "id": 26,
            "x":581,
            "y":512,
            "left": 28,
            "up": 24
        },
        {
            "id": 27,
            "x":77,
            "y":512,
            "down": 29,
            "left": 25
        },
        {
            "id": 28,
            "x":537,
            "y":512,
            "right": 26,
            "down": 30
        },
        {
            "id": 29,
            "x":77,
            "y":578,
            "right": 45,
            "left": 31,
            "up": 27
        },
        {
            "id": 30,
            "x":537,
            "y":578,
            "right": 32,
            "left": 46,
            "up": 28
        },
        {
            "id": 31,
            "x":33,
            "y":578,
            "right": 29,
            "down": 33
        },
        {
            "id": 32,
            "x":581,
            "y":578,
            "down": 34,
            "left": 30
        },
        {
            "id": 33,
            "x":33,
            "y":645,
            "right": 35,
            "up": 31
        },
        {
            "id": 34,
            "x":581,
            "y":645,
            "up": 32,
            "left": 36
        },
        {
            "id": 35,
            "x":274,
            "y":645,
            "right": 36,
            "left": 33,
            "up": 37
        },
        {
            "id": 36,
            "x":340,
            "y":645,
            "right": 34,
            "left": 35,
            "up": 38
        },
        {
            "id": 37,
            "x":274,
            "y":578,
            "down": 35,
            "left": 39
        },
        {
            "id": 38,
            "x":340,
            "y":578,
            "right": 40,
            "down": 36
        },
        {
            "id": 39,
            "x":208,
            "y":578,
            "right": 37,
            "up": 43
        },
        {
            "id": 40,
            "x":406,
            "y":578,
            "up": 44,
            "left": 38
        },
        {
            "id": 41,
            "x":142,
            "y":510,
            "right": 43,
            "down": 45,
            "up": 21
        },
        {
            "id": 42,
            "x":472,
            "y":510,
            "down": 46,
            "left": 44,
            "up": 22
        },
        {
            "id": 43,
            "x":208,
            "y":510,
            "right": 15,
            "left": 41,
            "down": 39
        },
        {
            "id": 44,
            "x":406,
            "y":510,
            "right": 42,
            "left": 16,
            "down": 40
        },
        {
            "id": 45,
            "x":142,
            "y":578,
            "up": 41,
            "left": 29
        },
        {
            "id": 46,
            "x":472,
            "y":578,
            "right": 30,
            "up": 42
        },
        {
            "id": 47,
            "x":406,
            "y":381,
            "down": 20,
            "left": 60,
            "up": 13
        },
        {
            "id": 48,
            "x":472,
            "y":182,
            "right": 49,
            "up": 53,
            "down": 14
        },
        {
            "id": 49,
            "x":581,
            "y":182,
            "up": 50,
            "left": 48
        },
        {
            "id": 50,
            "x":581,
            "y":116,
            "up": 51,
            "left": 53,
            "down": 49
        },
        {
            "id": 51,
            "x":581,
            "y":28,
            "down": 50,
            "left": 52
        },
        {
            "id": 52,
            "x":472,
            "y":28,
            "right": 51,
            "left": 4,
            "down": 53
        },
        {
            "id": 53,
            "x":472,
            "y":116,
            "right": 50,
            "left": 55,
            "down": 48,
            "up": 52
        },
        {
            "id": 54,
            "x":581,
            "y":315,
            "left": 14
        },
        {
            "id": 55,
            "x":406,
            "y":116,
            "right": 53,
            "left": 3,
            "down": 56
        },
        {
            "id": 56,
            "x":406,
            "y":182,
            "up": 55,
            "left": 57
        },
        {
            "id": 57,
            "x":340,
            "y":182,
            "right": 56,
            "down": 9
        },
        {
            "id": 58,
            "x":208,
            "y":247,
            "right": 8,
            "down": 59
        },
        {
            "id": 59,
            "x":208,
            "y":315,
            "left": 61,
            "up": 58,
            "down": 60
        },
        {
            "id": 60,
            "x":208,
            "y":381,
            "right": 47,
            "up": 59,
            "down": 19
        },
        {
            "id": 61,
            "x":142,
            "y":315,
            "right": 59,
            "left": 62,
            "down": 21,
            "up": 66
        },
        {
            "id": 62,
            "x":33,
            "y":315,
            "right": 61
        },
        {
            "id": 63,
            "x":33,
            "y":28,
            "right": 0,
            "down": 64
        },
        {
            "id": 64,
            "x":33,
            "y":116,
            "right": 67,
            "up": 63,
            "down": 65
        },
        {
            "id": 65,
            "x":33,
            "y":182,
            "right": 66,
            "up": 64
        },
        {
            "id": 66,
            "x":142,
            "y":182,
            "up": 67,
            "left": 65,
            "down": 61
        },
        {
            "id": 67,
            "x":142,
            "y":116,
            "right": 5,
            "left": 64,
            "up": 0,
            "down": 66
        },
        {
            "id": 68,
            "x":274,
            "y":315,
            "right":11
        },
        {
            "id": 69,
            "x":340,
            "y":315,
            "left": 11
        }
    ]
}